odoo10_addon_delivery_carrier_label_default-10.0.1.0.1-py3.8-nspkg.pth
odoo/addons/delivery_carrier_label_default/README.rst
odoo/addons/delivery_carrier_label_default/__init__.py
odoo/addons/delivery_carrier_label_default/__manifest__.py
odoo/addons/delivery_carrier_label_default/i18n/delivery_carrier_label_default.pot
odoo/addons/delivery_carrier_label_default/models/__init__.py
odoo/addons/delivery_carrier_label_default/models/stock_picking.py
odoo/addons/delivery_carrier_label_default/reports/report_default_label.xml
odoo/addons/delivery_carrier_label_default/reports/report_paper_format.xml
odoo/addons/delivery_carrier_label_default/static/description/icon.svg
odoo/addons/delivery_carrier_label_default/tests/__init__.py
odoo/addons/delivery_carrier_label_default/tests/test_print_label.py
odoo10_addon_delivery_carrier_label_default-10.0.1.0.1.dist-info/METADATA
odoo10_addon_delivery_carrier_label_default-10.0.1.0.1.dist-info/WHEEL
odoo10_addon_delivery_carrier_label_default-10.0.1.0.1.dist-info/namespace_packages.txt
odoo10_addon_delivery_carrier_label_default-10.0.1.0.1.dist-info/top_level.txt
odoo10_addon_delivery_carrier_label_default-10.0.1.0.1.dist-info/RECORD
