Metadata-Version: 2.1
Name: odoo10-addon-delivery-carrier-label-default
Version: 10.0.1.0.1
Summary: Default label for carrier labels
Home-page: https://github.com/OCA/delivery-carrier
Author: Camptocamp,Sunflower IT,Odoo Community Association (OCA)
Author-email: support@odoo-community.org
License: AGPL-3
Platform: UNKNOWN
Classifier: Programming Language :: Python
Classifier: Framework :: Odoo
Classifier: Framework :: Odoo :: 10.0
Classifier: License :: OSI Approved :: GNU Affero General Public License v3
Requires-Python: ~=2.7
Requires-Dist: odoo10-addon-base-delivery-carrier-label
Requires-Dist: odoo (<10.1dev,>=10.0)
